MANIFEST.in
setup.cfg
setup.py
confluent_flink_jars.egg-info/PKG-INFO
confluent_flink_jars.egg-info/SOURCES.txt
confluent_flink_jars.egg-info/dependency_links.txt
confluent_flink_jars.egg-info/top_level.txt
deps/lib/annotations-13.0.jar
deps/lib/commons-lang3-3.12.0.jar
deps/lib/confluent-flink-table-api-java-plugin-1.20-56.jar
deps/lib/error_prone_annotations-2.27.0.jar
deps/lib/flink-annotations-1.20.0.jar
deps/lib/flink-clients-1.20.0.jar
deps/lib/flink-core-1.20.0.jar
deps/lib/flink-core-api-1.20.0.jar
deps/lib/flink-python-1.20.0.jar
deps/lib/flink-runtime-1.20.0.jar
deps/lib/flink-shaded-asm-9-9.5-17.0.jar
deps/lib/flink-shaded-guava-31.1-jre-17.0.jar
deps/lib/flink-streaming-java-1.20.0.jar
deps/lib/flink-table-api-java-1.20.0.jar
deps/lib/flink-table-common-1.20.0.jar
deps/lib/gson-2.11.0.jar
deps/lib/gson-fire-1.9.0.jar
deps/lib/icu4j-67.1.jar
deps/lib/javax.annotation-api-1.3.2.jar
deps/lib/jsr305-1.3.9.jar
deps/lib/kotlin-stdlib-1.8.21.jar
deps/lib/kotlin-stdlib-common-1.9.10.jar
deps/lib/kotlin-stdlib-jdk7-1.8.21.jar
deps/lib/kotlin-stdlib-jdk8-1.8.21.jar
deps/lib/logging-interceptor-4.12.0.jar
deps/lib/okhttp-4.12.0.jar
deps/lib/okio-3.6.0.jar
deps/lib/okio-jvm-3.6.0.jar
deps/lib/slf4j-api-1.7.36.jar
deps/lib/snakeyaml-engine-2.6.jar
deps/pyflink/version.py