Metadata-Version: 2.4
Name: confluent-flink-jars
Version: 1.20.56
Summary: Confluent Apache Flink Jars
Home-page: https://confluent.io
Author: Confluent
Author-email: dev@confluent.io
License: https://www.apache.org/licenses/LICENSE-2.0
Classifier: Development Status :: 5 - Production/Stable
Classifier: Programming Language :: Python :: 3.9
Classifier: Programming Language :: Python :: 3.10
Classifier: Programming Language :: Python :: 3.11
Requires-Python: >=3.8
Dynamic: author
Dynamic: author-email
Dynamic: classifier
Dynamic: description
Dynamic: description-content-type
Dynamic: home-page
Dynamic: license
Dynamic: requires-python
Dynamic: summary
